proxyclass/__init__.py
proxyclass/annotation_utility.py
proxyclass/injection_utility.py
proxyclass/method_to_inject.py
proxyclass/proxy.py
proxy_class-0.0.1.dist-info/AUTHORS
proxy_class-0.0.1.dist-info/LICENSE
proxy_class-0.0.1.dist-info/METADATA
proxy_class-0.0.1.dist-info/WHEEL
proxy_class-0.0.1.dist-info/top_level.txt
proxy_class-0.0.1.dist-info/RECORD
